csv2fmdlrequirements.py
fmc
fmc.py
setup.py
fmdl.egg-info/PKG-INFO
fmdl.egg-info/SOURCES.txt
fmdl.egg-info/dependency_links.txt
fmdl.egg-info/top_level.txt
pytransform/__init__.py
pytransform/platforms/darwin/x86_64/_pytransform.dylib
pytransform/platforms/linux/x86/_pytransform.so
pytransform/platforms/linux/x86_64/_pytransform.so
pytransform/platforms/windows/x86/_pytransform.dll
pytransform/platforms/windows/x86_64/_pytransform.dll